Metadata-Version: 2.1
Name: sqlalchemy-pysqlite3
Version: 0.0.4
Summary: SQLAlchemy dialect to use pysqlite3 dbapi2
Home-page: https://github.com/hoehrmann/sqlalchemy-pysqlite3
Author: Bjoern Hoehrmann
Author-email: bjoern@hoehrmann.de
License: UNKNOWN
Platform: UNKNOWN
Classifier: Programming Language :: Python :: 3
Classifier: License :: OSI Approved :: MIT License
Classifier: Operating System :: OS Independent
Classifier: Topic :: Software Development :: Libraries :: Python Modules
Requires-Dist: pysqlite3
Requires-Dist: sqlalchemy
